django_zk_auth/__init__.py
django_zk_auth/admin.py
django_zk_auth/apps.py
django_zk_auth/auth_backend.py
django_zk_auth/exceptions.py
django_zk_auth/models.py
django_zk_auth/urls.py
django_zk_auth/utils.py
django_zk_auth/views.py
django_zk_auth/crypto/__init__.py
django_zk_auth/crypto/field_arithmetic.py
django_zk_auth/crypto/hash_utils.py
django_zk_auth/crypto/poseidon.py
django_zk_auth/crypto/proof_system.py
django_zk_auth/crypto/types.py
django_zk_auth/crypto/zk_system.py
tests/__init__.py
tests/conftest.py
tests/test_field_arithmetic.py
tests/test_hash_utils.py
tests/test_poseidon.py
tests/test_proof_system.py
tests/test_settings.py
tests/test_types.py
tests/test_zk_system.py
django_zk_auth-1.0.1.dist-info/METADATA
django_zk_auth-1.0.1.dist-info/WHEEL
django_zk_auth-1.0.1.dist-info/top_level.txt
django_zk_auth-1.0.1.dist-info/RECORD
